{"moduleCode":"AR5956E","title":"Topics in Design and Built Environment 5","description":"This module will involve a critical and thorough discussion of specific topics in design and the built environment.  Examples of topics that may be discussed are universal design, techniques and constructs of thinking, sustainable urban design, landscape and urban ecology,","moduleCredit":4.0,"department":"Architecture","faculty":"Design and Environment","acadYear":"2021/2022","semesterData":[{"semester":1,"examDuration":0,"timetable":[]}]}