{"moduleCode":"BMA5104A","title":"Topics in Global Strategic Management","description":"The course aims to provide participants with the basic\ntheoretical knowledge, skills, and sensitivities that will help\nthem deal effectively with key management issues and\nchallenges in today’s global business environment. We\nintend to explore the major issues and challenges facing\ncompanies with worldwide operations as seen by the\nmanagers themselves.","moduleCredit":2.0,"department":"BIZ Dean\u0027s Office","faculty":"NUS Business School","acadYear":"2021/2022","semesterData":[]}