{"acadYear":"2021/2022","description":"","title":"Business to Business Marketing","department":"BIZ Dean's Office","faculty":"NUS Business School","moduleCredit":"4","moduleCode":"BMA5528","semesterData":[{"semester":3,"timetable":[{"classNo":"P1","startTime":"1830","endTime":"2200","weeks":{"start":"2022-05-10","end":"2022-06-14"},"venue":"BIZ1-0302","day":"Tuesday","lessonType":"Sectional Teaching","size":60,"covidZone":"B"},{"classNo":"P1","startTime":"1830","endTime":"2200","weeks":{"start":"2022-05-12","end":"2022-06-16"},"venue":"BIZ1-0302","day":"Thursday","lessonType":"Sectional Teaching","size":60,"covidZone":"B"}],"covidZones":["B"]}]}
