{"moduleCode":"BT5153","title":"Applied Machine Learning for Business Analytics","description":"This module aims to prepare graduate students for advanced data science topics and their application in business analytics. The module will investigate the integration of business know-how and advanced analytics technologies. The key deliverable of this module will be the skills to build the practical data science pipeline and utilize state of the art in machine learning.","moduleCredit":4.0,"department":"Information Systems and Analytics","faculty":"Computing","prerequisite":"DSC5106 Foundation in Data Analytics I OR DSC5103 Statistics","preclusion":"BT4222, CS5246","acadYear":"2021/2022","attributes":{"mpes1":false,"mpes2":true,"su":false},"semesterData":[{"semester":2,"examDuration":0,"timetable":[{"classNo":"1","startTime":1830,"endTime":2030,"venue":"E-Learn_C","day":"Friday","lessonType":"Lecture","size":150}]}]}