{"moduleCode":"CE5603","title":"Engineering Economics \u0026 Project Evaluation","description":"This module equips students with the analytical methods and techniques to evaluate projects from an economic perspective. The purpose of the evaluation is to enable rational project selection and capital allocation taking into consideration factors like risk, uncertainty, inflation, and foreign exchange.","moduleCredit":4.0,"department":"Civil and Environmental Engineering","faculty":"Engineering","acadYear":"2021/2022","attributes":{"mpes1":false,"mpes2":false,"su":false},"semesterData":[]}