{"moduleCode":"DBA3761","title":"Topics in Business Analytics","description":"Business analytics, built on the prevalence of data, is being applied to all aspects of business to\nenhance decision making. This module intends to expose students to recent developments in the\ntheory, technology and application of analytics in business. This module serves as a placeholder for\ncovering latest developments in business analytics (in theory, technology and/or applications) that are\nnot covered by other BA modules.\n\nThis module is also a placeholder for experimental or ad hoc elective modules in business analytics.","moduleCredit":4.0,"department":"Analytics and Operations","faculty":"NUS Business School","prerequisite":"DAO1704 Decision Analytics using Spreadsheets\nDAO2702 Programming for Business Analytics","acadYear":"2021/2022","semesterData":[]}