{"moduleCode":"DOS3701","title":"Supply Chain Management","description":"This course considers the operation of a supply chain from a managerial perspective, serving two main objectives: to provide tools for design, analysis, management and performance improvement of supply chains, and to introduce and discuss recent influential innovations in supply chain management such as B2B portals. Students will be taught to appreciate the need to balance between responsiveness and efficiency in the four major components of the chain: Inventory, Transportation, Facilities, and Information. These four components will be introduced to the students through suitable mathematical and behavioural models. It is recommended that students have some understanding of the Internet and e-business.","moduleCredit":4.0,"department":"Analytics and Operations","faculty":"NUS Business School","prerequisite":"DAO2703","preclusion":"DSC3201","acadYear":"2021/2022","attributes":{"mpes1":true,"mpes2":true,"su":false},"semesterData":[{"semester":1,"examDate":"Dec 1, 2021, 1:00:00 PM","examDuration":120,"timetable":[{"classNo":"A1","startTime":1200,"endTime":1500,"venue":"BIZ2-0509","day":"Thursday","lessonType":"Sectional Teaching","size":65},{"classNo":"A2","startTime":1200,"endTime":1500,"venue":"BIZ1-0204","day":"Friday","lessonType":"Sectional Teaching","size":65}]},{"semester":2,"examDate":"Apr 25, 2022, 5:00:00 PM","examDuration":120,"timetable":[{"classNo":"A2","startTime":1500,"endTime":1800,"venue":"BIZ2-0413A","day":"Tuesday","lessonType":"Sectional Teaching","size":45},{"classNo":"A1","startTime":1500,"endTime":1800,"venue":"BIZ1-0201","day":"Friday","lessonType":"Sectional Teaching","size":45}]}]}