{"moduleCode":"EC5372","title":"Growth Theory","description":"This module introduces several important economic growth models.  The main focuses will be on studying the underlying sources of economic growth and analyzing how government policies influence the growth process.  Major topics include exogenous growth models, endogenous growth models with capital accumulation, technological progress through R \u0026 D and growth, growth models with learning-by-doing, diffusion of technology and growth, growth in open economy, and empirical studies of economic growth.","moduleCredit":4.0,"department":"Economics","faculty":"Arts and Social Science","preclusion":"EC5206","acadYear":"2021/2022","semesterData":[]}