{"moduleCode":"ESE5601","title":"Environmental Risk Assessment","description":"The objective of this module is to examine the fundamental principles governing toxic contaminant exposure and risk to humans and ecosystems. The course will cover necessary aspects of probability and statistics, physical and chemical behaviour of key priority pollutants, mass transfer and exposure pathways of the contaminants, human and environmental toxicology, and methodologies for risk assessment. The\ncourse will also involve several case studies of remediation technology applications with a focus on understanding how human and environmental risk is managed in a real\nlife situation.","moduleCredit":4.0,"department":"Civil and Environmental Engineering","faculty":"Engineering","prerequisite":"ESE4 standing or higher","acadYear":"2021/2022","attributes":{"mpes1":false,"mpes2":false,"su":false},"semesterData":[]}