{"moduleCode":"FIN4118","title":"Equity Research Seminar","description":"This course seeks to highlight \u0026 provide the rigour and skills needed for stock selection using a fundamental research approach. Moreover it provides the understanding needed to know how these qualitative skills are applied to portfolio management in the investment management industry.\nIn addition to the above, this course also introduces students to the top down approach of portfolio management and how portfolios with multiple countries can be constructed.","moduleCredit":4.0,"department":"Finance","faculty":"NUS Business School","prerequisite":"FIN3101","acadYear":"2021/2022","semesterData":[{"semester":2,"examDuration":0,"timetable":[{"classNo":"A1","startTime":1500,"endTime":1800,"venue":"LT18","day":"Tuesday","lessonType":"Sectional Teaching","size":31}]}]}