{"moduleCode":"GL4882A","title":"Development and the Globalisation of Food","description":"The module will be organised around the following four topics. First, the vision of agriculture found in early development thought; second the structural transformations of agriculture in the twentieth century in terms of production and trade; third, an examination of states that have resisted the globalising tide in order to determine whether their domestic policies qualify as “development”; and finally the possibility of decoupling development and globalisation.","moduleCredit":5.0,"department":"Political Science","faculty":"Arts and Social Science","prerequisite":"Completed 80 MCs, including 28 MCs in GL/GL recognised non?language modules, or 28 MCs in PS, with a minimum CAP of 3.20 or be on the Honours track.","acadYear":"2021/2022","semesterData":[]}