{"moduleCode":"ME4265","title":"Automotive Body \u0026 Chassis Engineering","description":"This module will help students understand the specifications for the design of body and chassis systems, design architectures, methods of component engineering, material selection, corrosion treatment \u0026 water management, manufacturing methods.","moduleCredit":4.0,"department":"Mechanical Engineering","faculty":"Engineering","prerequisite":"ME 2113 – Mechanics of Materials","acadYear":"2021/2022","semesterData":[]}