{"moduleCode":"MNO4751","title":"Adv Independent Study in Leadership \u0026 Human Capital Mgt","description":"Advanced Independent Study Modules (ISMs) are for senior students who are in the BBA and BBA(Acc) honors programs with the requisite background to work closely with an instructor on a well-defined project in the respective specialization areas. (The modules may also be made available to students who are eligible for admission into the honors programs but choose to pursue the non-honors course of study.) Students will hone their research and report-writing skills while tackling a business issue under the guidance of the instructor.","moduleCredit":4.0,"department":"Management and Organisation","faculty":"NUS Business School","prerequisite":"MNO1706 Organisational Behaviour or \nMNO1706X Organisational Behavior or \nPL3239 Industrial and Organisational Psychology and \nMNO2705 Leadership and Decision Making under Uncertainty","acadYear":"2021/2022","semesterData":[{"semester":1,"examDuration":0,"timetable":[]}]}