{"moduleCode":"MS3213","title":"Ideology \u0026 Ideas on Malay Development","description":"This module seeks to expose students to the thinking of Malay elite on Malay development. In discussing the ideas of the elite, various ideologies and styles of thought would be identified and examined as to their influence on development philosophy. A critique of the thinking of the Malay elite would be attempted. The conditioning of feudalism, colonialism, Islam, nationalism and capitalism on development thinking would be critically analysed. The module is designed for students interested in issues of Malay development and intellectual history.","moduleCredit":4.0,"department":"Malay Studies","faculty":"Arts and Social Science","acadYear":"2021/2022","attributes":{"mpes1":false,"mpes2":true,"su":false},"semesterData":[{"semester":2,"examDuration":0,"timetable":[{"classNo":"1","startTime":900,"endTime":1200,"venue":"AS8-0402","day":"Wednesday","lessonType":"Seminar-Style Module Class","size":30}]}]}