{"moduleCode":"MUA4161","title":"Advanced Studies on Principal Instrument","description":"Focused study on an instrument forms the central pillar for\nthe BMus Majors in piano, strings, brass, wind and\npercussion. Normally undertaken in the fourth year of\nstudy, this module usually begins the journey for students\ntowards their capstone Senior Recital and assures that\ntheir instrumental readiness is appropriate for the next\nstage in their professional journey, whether to graduate\nschool or into prefoessional work.","moduleCredit":6.0,"department":"YSTCM Dean\u0027s Office","faculty":"YST Conservatory of Music","prerequisite":"MUA3162","acadYear":"2021/2022","semesterData":[{"semester":1,"examDuration":0,"timetable":[]},{"semester":2,"examDuration":0,"timetable":[]}]}