{"moduleCode":"NM2220","title":"Introduction to Media Writing","description":"This introductory module provides instruction and practice in writing for the mass media, including the Internet. It explores the similarities and differences in writing styles for all mass media and for the professions of journalism, public affairs, public relations, advertising and telecommunications. It emphasizes accuracy, responsibility, clarity and style in presenting information through the various channels of mass communication. It surveys communication theories of various professions that communicate via the mass media, establishing the basis for advanced studies in writing and communication. It helps students acquire the writing skills they need in communication management careers","moduleCredit":4.0,"department":"Communications and New Media","faculty":"Arts and Social Science","acadYear":"2021/2022","attributes":{"mpes1":true,"mpes2":true,"su":true},"semesterData":[{"semester":1,"examDuration":0,"timetable":[{"classNo":"1","startTime":1400,"endTime":1600,"venue":"E-Learn_C","day":"Thursday","lessonType":"Lecture","size":104},{"classNo":"W3","startTime":1400,"endTime":1600,"venue":"E-Learn_C","day":"Wednesday","lessonType":"Tutorial","size":26},{"classNo":"W4","startTime":1800,"endTime":2000,"venue":"E-Learn_C","day":"Friday","lessonType":"Tutorial","size":26},{"classNo":"W1","startTime":1000,"endTime":1200,"venue":"E-Learn_C","day":"Monday","lessonType":"Tutorial","size":26},{"classNo":"W2","startTime":1200,"endTime":1400,"venue":"E-Learn_C","day":"Monday","lessonType":"Tutorial","size":26},{"classNo":"W5","startTime":1400,"endTime":1600,"venue":"E-Learn_C","day":"Monday","lessonType":"Tutorial","size":23}]},{"semester":2,"examDate":"May 5, 2022, 1:00:00 PM","examDuration":120,"timetable":[{"classNo":"W1","startTime":1000,"endTime":1200,"venue":"AS6-0215B","day":"Monday","lessonType":"Tutorial","size":20},{"classNo":"W2","startTime":1200,"endTime":1400,"venue":"AS6-0215B","day":"Monday","lessonType":"Tutorial","size":20},{"classNo":"W3","startTime":1400,"endTime":1600,"venue":"AS6-0215B","day":"Tuesday","lessonType":"Tutorial","size":20},{"classNo":"W4","startTime":1600,"endTime":1800,"venue":"AS6-0215B","day":"Tuesday","lessonType":"Tutorial","size":20},{"classNo":"1","startTime":1000,"endTime":1200,"venue":"LT10","day":"Friday","lessonType":"Lecture","size":80}]}]}