{"moduleCode":"NUR3105C","title":"Clinical Practice: Community Care II","description":"The module enables students to integrate nursing theory and clinical knowledge through experience in community health care settings, such as home/ transition care/ intermediate long term care and primary health care settings. Students will focus on planning, implementing and evaluating nursing care for clients in the community health services and facilities. Students will apply knowledge from nursing and clinical sciences in the integrated clinical management, health promotion and education of patients. Attendance for the scheduled clinical practicum is mandatory.","moduleCredit":2.0,"department":"Alice Lee Center for Nursing Studies","faculty":"Yong Loo Lin Sch of Medicine","preclusion":"NUR3105A Nursing Practice Experience 3.1","acadYear":"2021/2022","attributes":{"mpes1":true,"mpes2":true,"su":false},"semesterData":[]}