{"moduleCode":"PP6708","title":"Research Design in Public Policy","description":"This is the first and introductory of a three-module series on\nresearch methods that is required for all first-year PhD\nstudents in Public Policy. The purposes of the module are to\nintroduce to students key concepts in research methods,\nand to help them to develop skills in the design of empirical\nresearch used in the analysis of policy problems. The aim is\nthat students are able to apply various research designs in\nconducting rigorous policy research in their chosen fields, as\nwell as develop the ability to critically evaluate policy\nresearch outputs.","moduleCredit":4.0,"department":"LKYSPP Dean\u0027s Office","faculty":"LKY School of Public Policy","acadYear":"2021/2022","semesterData":[{"semester":1,"examDuration":0,"timetable":[{"classNo":"1","startTime":1400,"endTime":1700,"venue":"LKY_SR2-3","day":"Wednesday","lessonType":"Lecture","size":10}]}]}