{"moduleCode":"PR5230","title":"Pharmacoeconomics and Outcomes Research","description":"Pharmacoeconomics and health outcomes research is a relatively new and rapidly evolving field. It encompasses both economic and humanistic issues and serves as a major tool that aims to decrease health expenditures and optimise healthcare results. This is particularly relevant in the provision of pharmaceutical care by practising pharmacists. Knowledge of this discipline aids the pharmacist in making decisions for the most optimal pharmaceutical products and health services that allow for fair and efficient utilisation of healthcare resources.","moduleCredit":4.0,"department":"Pharmacy","faculty":"Science","prerequisite":"Acceptance into PharmD or relevant degree or special permission","acadYear":"2021/2022","attributes":{"mpes1":false,"mpes2":true,"su":false},"semesterData":[{"semester":2,"examDuration":0,"timetable":[{"classNo":"1","startTime":1830,"endTime":2030,"venue":"MD1-06-03M","day":"Wednesday","lessonType":"Lecture","size":10}]}]}