{"moduleCode":"PS3262","title":"Managing Non-Profit Organisations","description":"This module presents a broad overview of non-profit organization management. Based on public administration and strategic management theory, it focuses on practical problem-solving ideas. Topics to be considered include: 1) shaping an organisation’s vision and mission, 2) SWOT analysis, 3) decision-making, 4) establishing strategic management capacity, 5) inter-organizational cooperation and partnership, and 6) other management techniques.","moduleCredit":4.0,"department":"Political Science","faculty":"Arts and Social Science","acadYear":"2021/2022","attributes":{"mpes1":true,"mpes2":false,"su":false},"semesterData":[{"semester":1,"examDuration":0,"timetable":[{"classNo":"1","startTime":800,"endTime":1000,"venue":"E-Learn_C","day":"Thursday","lessonType":"Lecture","size":75},{"classNo":"D1","startTime":1200,"endTime":1400,"venue":"E-Learn_C","day":"Wednesday","lessonType":"Tutorial","size":25},{"classNo":"D2","startTime":1200,"endTime":1400,"venue":"E-Learn_C","day":"Thursday","lessonType":"Tutorial","size":25},{"classNo":"E1","startTime":1200,"endTime":1400,"venue":"E-Learn_C","day":"Tuesday","lessonType":"Tutorial","size":25}]}]}