{"moduleCode":"SPH5409","title":"Qualitative Methods in Public Health","description":"This module will familiarize students with various data collection and analytic methods in qualitative research, allowing them to apply appropriate methods with relevant ethical considerations. Students will be guided through each step of the qualitative research process starting with the underlying principles of qualitative approaches and moving on to study design, sampling, data collection and analysis. Students will have hands-on practical experience applying the various data collection methods; as well as learning practical techniques on how to conduct and write the analysis.","moduleCredit":4.0,"department":"SSH School of Public Health Dean\u0027s Office","faculty":"SSH School of Public Health","preclusion":"CO5233 Qualitative Methods in Public Health","acadYear":"2021/2022","attributes":{"mpes1":true,"mpes2":true,"su":false},"semesterData":[{"semester":1,"examDuration":0,"timetable":[{"classNo":"1","startTime":1400,"endTime":1700,"venue":"E-Learn_B","day":"Friday","lessonType":"Lecture","size":40}]},{"semester":2,"examDuration":0,"timetable":[{"classNo":"1","startTime":1800,"endTime":2100,"venue":"MD1-0903EF","day":"Tuesday","lessonType":"Lecture","size":60}]}]}