{"moduleCode":"YCC1122","title":"Quantitative Reasoning","description":"Quantitative Reasoning is concerned to strengthen what might be called numeracy or quantitative literacy by exploring some basic topics related to algorithmic thinking and statistical inference. Among the topics considered are formal logic, probability, surveys and sampling, hypothesis testing, correlation and regression, and prospect theory.","moduleCredit":5.0,"department":"Yale-NUS College","faculty":"Yale-NUS College","acadYear":"2021/2022","semesterData":[{"semester":1,"examDuration":0,"timetable":[{"classNo":"L12","startTime":1600,"endTime":1800,"venue":"E-Learn_A","day":"Monday","lessonType":"Seminar-Style Module Class","size":18},{"classNo":"L5","startTime":1230,"endTime":1430,"venue":"Y-CompLab","day":"Monday","lessonType":"Seminar-Style Module Class","size":18},{"classNo":"L12","startTime":1600,"endTime":1800,"venue":"E-Learn_A","day":"Thursday","lessonType":"Seminar-Style Module Class","size":18},{"classNo":"L5","startTime":1230,"endTime":1430,"venue":"E-Learn_A","day":"Thursday","lessonType":"Seminar-Style Module Class","size":18},{"classNo":"L11","startTime":1800,"endTime":2000,"venue":"ERC-ALR","day":"Monday","lessonType":"Seminar-Style Module Class","size":18},{"classNo":"L4","startTime":1230,"endTime":1430,"venue":"Y-CR15","day":"Monday","lessonType":"Seminar-Style Module Class","size":20},{"classNo":"L11","startTime":1800,"endTime":2000,"venue":"ERC-ALR","day":"Thursday","lessonType":"Seminar-Style Module Class","size":18},{"classNo":"L14","startTime":1730,"endTime":1930,"venue":"Y-PerfHall","day":"Monday","lessonType":"Seminar-Style Module Class","size":18},{"classNo":"L14","startTime":1730,"endTime":1930,"venue":"Y-PerfHall","day":"Thursday","lessonType":"Seminar-Style Module Class","size":18},{"classNo":"L8","startTime":1730,"endTime":1930,"venue":"E-Learn_A","day":"Thursday","lessonType":"Seminar-Style Module Class","size":18},{"classNo":"L10","startTime":1600,"endTime":1800,"venue":"ERC-ALR","day":"Monday","lessonType":"Seminar-Style Module Class","size":18},{"classNo":"L8","startTime":1730,"endTime":1930,"venue":"E-Learn_A","day":"Monday","lessonType":"Seminar-Style Module Class","size":18},{"classNo":"L9","startTime":1600,"endTime":1800,"venue":"Y-CR17","day":"Monday","lessonType":"Seminar-Style Module Class","size":18},{"classNo":"L9","startTime":1600,"endTime":1800,"venue":"Y-CR17","day":"Thursday","lessonType":"Seminar-Style Module Class","size":18},{"classNo":"L13","startTime":1600,"endTime":1800,"venue":"Y-GLRm1","day":"Thursday","lessonType":"Seminar-Style Module Class","size":20},{"classNo":"L7","startTime":1230,"endTime":1430,"venue":"Y-LT1","day":"Monday","lessonType":"Seminar-Style Module Class","size":18},{"classNo":"L6","startTime":1230,"endTime":1430,"venue":"Y-BlackBox","day":"Monday","lessonType":"Seminar-Style Module Class","size":18},{"classNo":"L6","startTime":1230,"endTime":1430,"venue":"Y-BlackBox","day":"Thursday","lessonType":"Seminar-Style Module Class","size":18},{"classNo":"L7","startTime":1230,"endTime":1430,"venue":"Y-LT1","day":"Thursday","lessonType":"Seminar-Style Module Class","size":18},{"classNo":"L1","startTime":1230,"endTime":1430,"venue":"Y-TCTLT","day":"Thursday","lessonType":"Seminar-Style Module Class","size":19},{"classNo":"L2","startTime":1230,"endTime":1430,"venue":"Y-CR17","day":"Thursday","lessonType":"Seminar-Style Module Class","size":18},{"classNo":"L1","startTime":1230,"endTime":1430,"venue":"Y-TCTLT","day":"Monday","lessonType":"Seminar-Style Module Class","size":19},{"classNo":"L3","startTime":1230,"endTime":1430,"venue":"Y-GLRm1","day":"Monday","lessonType":"Seminar-Style Module Class","size":18},{"classNo":"L4","startTime":1230,"endTime":1430,"venue":"Y-CR15","day":"Thursday","lessonType":"Seminar-Style Module Class","size":20},{"classNo":"L10","startTime":1600,"endTime":1800,"venue":"ERC-ALR","day":"Thursday","lessonType":"Seminar-Style Module Class","size":18},{"classNo":"L13","startTime":1600,"endTime":1800,"venue":"Y-GLRm1","day":"Monday","lessonType":"Seminar-Style Module Class","size":20},{"classNo":"L2","startTime":1230,"endTime":1430,"venue":"Y-CR17","day":"Monday","lessonType":"Seminar-Style Module Class","size":18},{"classNo":"L3","startTime":1230,"endTime":1430,"venue":"Y-GLRm1","day":"Thursday","lessonType":"Seminar-Style Module Class","size":18}]}]}