{"moduleCode":"YSC4230","title":"Programming Language Design and Implementation","description":"We study the theory of programming languages and their implementation.  Topics may include automata, semantics, verification, interpreters, compilers, and runtime systems.  This course includes a substantial project.","moduleCredit":5.0,"department":"Yale-NUS College","faculty":"Yale-NUS College","prerequisite":"YSC2229 Introductory Data Structures and Algorithms (or previously YSC2204 Fundamentals of Programming) or with the permission of the instructor.","preclusion":"YSC3208 Programming Language Design and Implementation","corequisite":"YSC3207 Principles and Tools of Software Development or with the permission of the instructor.","acadYear":"2021/2022","attributes":{"mpes1":true,"mpes2":false,"su":false},"semesterData":[{"semester":1,"examDate":"Nov 27, 2021, 9:00:00 AM","examDuration":180,"timetable":[{"classNo":"1","startTime":900,"endTime":1200,"venue":"Y-ELMCL","day":"Wednesday","lessonType":"Seminar-Style Module Class","size":18}]}]}