{"moduleCode":"YSS4205","title":"Chinese Foreign Policy","description":"Students will gain a deeper understanding of the major contours of the debate and discussion on China’s contemporary international relations. The course examines the political, diplomatic, military, and economic challenges facing China under conditions of uncertainty in the regional and international system and the processes through which China responds to and manages these external challenges. The course will analyse how existing theories of international relations and foreign policy analysis apply to China to gain a deeper appreciation of the factors that undergird conflict and cooperation in Chinese foreign policy.","moduleCredit":5.0,"department":"Yale-NUS College","faculty":"Yale-NUS College","prerequisite":"YSS2202 International Relations or with the permission of the instructor.","acadYear":"2021/2022","attributes":{"mpes1":true,"mpes2":false,"su":false},"semesterData":[{"semester":1,"examDuration":0,"timetable":[{"classNo":"1","startTime":1300,"endTime":1600,"venue":"Y-KChanrai","day":"Tuesday","lessonType":"Seminar-Style Module Class","size":18}]}]}